LICENSE.md
MANIFEST.in
README.md
requirements.txt
setup.cfg
setup.py
gramfuzz/__init__.py
gramfuzz/errors.py
gramfuzz/fields.py
gramfuzz/rand.py
gramfuzz/utils.py
gramfuzz.egg-info/PKG-INFO
gramfuzz.egg-info/SOURCES.txt
gramfuzz.egg-info/dependency_links.txt
gramfuzz.egg-info/requires.txt
gramfuzz.egg-info/top_level.txt
tests/__init__.py
tests/test_basic.py
tests/test_examples.py
tests/test_fuzzer.py
tests/test_shortest_path.py