Metadata-Version: 1.2
Name: gramfuzz
Version: 1.4.1
Summary: gramfuzz is a python-based grammar fuzzer
Home-page: https://github.com/d0c-s4vage/gramfuzz
Author: James 'd0c_s4vage' Johnson
Author-email: d0c.s4vage@gmail.com
Maintainer: James 'd0c_s4vage' Johnson
License: MIT
Download-URL: https://github.com/d0c-s4vage/gramfuzz/tarball/v1.4.1
Platform: Cross Platform
Classifier: Programming Language :: Python :: 2
Classifier: Programming Language :: Python :: 3
